origami/__init__.py
origami/cli/__init__.py
origami/cli/main.py
origami/cli/predict.py
origami/cli/train.py
origami/cli/utils.py
origami/datasets/__init__.py
origami/datasets/dungeons.py
origami/inference/__init__.py
origami/inference/autocomplete.py
origami/inference/batch_sampler.py
origami/inference/embedder.py
origami/inference/mc_estimator.py
origami/inference/metrics.py
origami/inference/predictor.py
origami/inference/rejection_estimator.py
origami/inference/sampler.py
origami/model/__init__.py
origami/model/origami.py
origami/model/positions.py
origami/model/vpda.py
origami/preprocessing/__init__.py
origami/preprocessing/df_dataset.py
origami/preprocessing/encoder.py
origami/preprocessing/pipelines.py
origami/preprocessing/pipes.py
origami/preprocessing/utils.py
origami/utils/__init__.py
origami/utils/common.py
origami/utils/config.py
origami/utils/guild.py
origami/utils/query_utils.py
origami_ml-0.2.0.dist-info/licenses/LICENSE
origami_ml-0.2.0.dist-info/METADATA
origami_ml-0.2.0.dist-info/WHEEL
origami_ml-0.2.0.dist-info/entry_points.txt
origami_ml-0.2.0.dist-info/top_level.txt
origami_ml-0.2.0.dist-info/RECORD
