Metadata-Version: 2.4
Name: origami-ml
Version: 0.2.0
Summary: An ML classifier model to make predictions from semi-structured data.
Home-page: https://github.com/rueckstiess/origami
Author: Thomas Rueckstiess
Author-email: Thomas Rueckstiess <me@tomr.au>
Project-URL: Homepage, https://github.com/rueckstiess/origami
Project-URL: Repository, https://github.com/rueckstiess/origami
Project-URL: Issues, https://github.com/rueckstiess/origami/issues
Classifier: Development Status :: 4 - Beta
Classifier: Intended Audience :: Science/Research
Classifier: License :: OSI Approved :: Apache Software License
Classifier: Programming Language :: Python :: 3
Classifier: Programming Language :: Python :: 3.11
Classifier: Topic :: Scientific/Engineering :: Artificial Intelligence
Requires-Python: >=3.10
License-File: LICENSE
Requires-Dist: click>=8.1.7
Requires-Dist: click-option-group>=0.5.6
Requires-Dist: guildai>=0.9.0
Requires-Dist: lightgbm>=4.5.0
Requires-Dist: matplotlib>=3.9.2
Requires-Dist: mdbrtools>=0.1.1
Requires-Dist: numpy>=1.26.4
Requires-Dist: omegaconf>=2.3.0
Requires-Dist: openml>=0.15.1
Requires-Dist: pandas>=2.2.3
Requires-Dist: pymongo>=4.8.0
Requires-Dist: python-dotenv>=1.0.1
Requires-Dist: scikit-learn>=1.5.2
Requires-Dist: torch>=2.4.1
Requires-Dist: tqdm>=4.66.4
Requires-Dist: xgboost>=2.1.3
Provides-Extra: dev
Requires-Dist: jupyter>=1.1.1; extra == "dev"
Requires-Dist: jupyter-contrib-nbextensions>=0.7.0; extra == "dev"
Requires-Dist: pytest>=8.3.3; extra == "dev"
Requires-Dist: ruff>=0.9.3; extra == "dev"
Dynamic: author
Dynamic: home-page
Dynamic: license-file
Dynamic: requires-python
